TrialPy2/RCFA.py
TrialPy2/_RCSingle.py
TrialPy2/__init__.py
TrialPy2/_arrangeCal.py
TrialPy2/_forcesCal.py
TrialPy2-0.0.0.1.dist-info/LICENSE
TrialPy2-0.0.0.1.dist-info/METADATA
TrialPy2-0.0.0.1.dist-info/WHEEL
TrialPy2-0.0.0.1.dist-info/top_level.txt
TrialPy2-0.0.0.1.dist-info/RECORD
